{
  "metadata": {
    "filename": "pl090.cbl",
    "filepath": "purchase/pl090.cbl",
    "parseTimestamp": "2025-09-19T16:22:53.825Z",
    "fileSize": 9643,
    "lastModified": "2025-08-26T15:57:37.000Z",
    "parseVersion": "1.0",
    "dialect": "GnuCOBOL"
  },
  "identification": {
    "programId": "pl090",
    "programType": "sub",
    "author": "Cis Cobol Conversion By V B Coen FBCS, FIDM, FIDPM, 17/04/84",
    "dateWritten": null,
    "dateCompiled": null,
    "remarks": [
      "Payment Proof Sort."
    ]
  },
  "environment": {
    "sourceComputer": null,
    "objectComputer": null,
    "fileControl": []
  },
  "data": {
    "fileSection": [],
    "workingStorage": {
      "fields": [
        {
          "level": "77",
          "name": "ws-reply",
          "picture": "x",
          "usage": null,
          "value": null,
          "occurs": null,
          "redefines": null,
          "children": []
        },
        {
          "level": "01",
          "name": "Dummies-4-Unused-ACAS-FH-Calls",
          "picture": null,
          "usage": null,
          "value": null,
          "occurs": null,
          "redefines": null,
          "children": [
            {
              "level": "03",
              "name": "Default-Record",
              "picture": "x",
              "usage": null,
              "value": null,
              "occurs": null,
              "redefines": null,
              "children": []
            },
            {
              "level": "03",
              "name": "Final-Record",
              "picture": "x",
              "usage": null,
              "value": null,
              "occurs": null,
              "redefines": null,
              "children": []
            },
            {
              "level": "03",
              "name": "System-Record-4",
              "picture": "x",
              "usage": null,
              "value": null,
              "occurs": null,
              "redefines": null,
              "children": []
            },
            {
              "level": "03",
              "name": "WS-Ledger-Record",
              "picture": "x",
              "usage": null,
              "value": null,
              "occurs": null,
              "redefines": null,
              "children": []
            },
            {
              "level": "03",
              "name": "WS-Posting-Record",
              "picture": "x",
              "usage": null,
              "value": null,
              "occurs": null,
              "redefines": null,
              "children": []
            },
            {
              "level": "03",
              "name": "WS-Batch-Record",
              "picture": "x",
              "usage": null,
              "value": null,
              "occurs": null,
              "redefines": null,
              "children": []
            },
            {
              "level": "03",
              "name": "WS-IRS-Posting-Record",
              "picture": "x",
              "usage": null,
              "value": null,
              "occurs": null,
              "redefines": null,
              "children": []
            },
            {
              "level": "03",
              "name": "WS-Stock-Audit-Record",
              "picture": "x",
              "usage": null,
              "value": null,
              "occurs": null,
              "redefines": null,
              "children": []
            },
            {
              "level": "03",
              "name": "WS-Stock-Record",
              "picture": "x",
              "usage": null,
              "value": null,
              "occurs": null,
              "redefines": null,
              "children": []
            },
            {
              "level": "03",
              "name": "WS-Sales-Record",
              "picture": "x",
              "usage": null,
              "value": null,
              "occurs": null,
              "redefines": null,
              "children": []
            },
            {
              "level": "03",
              "name": "WS-Value-Record",
              "picture": "x",
              "usage": null,
              "value": null,
              "occurs": null,
              "redefines": null,
              "children": []
            },
            {
              "level": "03",
              "name": "WS-Delivery-Record",
              "picture": "x",
              "usage": null,
              "value": null,
              "occurs": null,
              "redefines": null,
              "children": []
            },
            {
              "level": "03",
              "name": "WS-Analysis-Record",
              "picture": "x",
              "usage": null,
              "value": null,
              "occurs": null,
              "redefines": null,
              "children": []
            },
            {
              "level": "03",
              "name": "WS-Del-Inv-Nos-Record",
              "picture": "x",
              "usage": null,
              "value": null,
              "occurs": null,
              "redefines": null,
              "children": []
            },
            {
              "level": "03",
              "name": "WS-Purch-Record",
              "picture": "x",
              "usage": null,
              "value": null,
              "occurs": null,
              "redefines": null,
              "children": []
            },
            {
              "level": "03",
              "name": "WS-Pay-Record",
              "picture": "x",
              "usage": null,
              "value": null,
              "occurs": null,
              "redefines": null,
              "children": []
            },
            {
              "level": "03",
              "name": "WS-Invoice-Record",
              "picture": "x",
              "usage": null,
              "value": null,
              "occurs": null,
              "redefines": null,
              "children": []
            },
            {
              "level": "03",
              "name": "WS-OTM3-Record",
              "picture": "x",
              "usage": null,
              "value": null,
              "occurs": null,
              "redefines": null,
              "children": []
            },
            {
              "level": "03",
              "name": "WS-PInvoice-Record",
              "picture": "x",
              "usage": null,
              "value": null,
              "occurs": null,
              "redefines": null,
              "children": []
            }
          ]
        },
        {
          "level": "01",
          "name": "File-Info",
          "picture": null,
          "usage": null,
          "value": "zero",
          "occurs": null,
          "redefines": null,
          "children": [
            {
              "level": "05",
              "name": "File-Size-Bytes",
              "picture": "9(18)",
              "usage": null,
              "value": null,
              "occurs": null,
              "redefines": null,
              "children": []
            },
            {
              "level": "05",
              "name": "Mod-DD",
              "picture": "9(2)",
              "usage": null,
              "value": null,
              "occurs": null,
              "redefines": null,
              "children": []
            },
            {
              "level": "05",
              "name": "Mod-MO",
              "picture": "9(2)",
              "usage": null,
              "value": null,
              "occurs": null,
              "redefines": null,
              "children": []
            },
            {
              "level": "05",
              "name": "Mod-YYYY",
              "picture": "9(4)",
              "usage": null,
              "value": null,
              "occurs": null,
              "redefines": null,
              "children": []
            },
            {
              "level": "05",
              "name": "Mod-HH",
              "picture": "9(2)",
              "usage": null,
              "value": null,
              "occurs": null,
              "redefines": null,
              "children": []
            },
            {
              "level": "05",
              "name": "Mod-MM",
              "picture": "9(2)",
              "usage": null,
              "value": null,
              "occurs": null,
              "redefines": null,
              "children": []
            },
            {
              "level": "05",
              "name": "Mod-SS",
              "picture": "9(2)",
              "usage": null,
              "value": null,
              "occurs": null,
              "redefines": null,
              "children": []
            },
            {
              "level": "05",
              "name": "filler",
              "picture": "9(2)",
              "usage": null,
              "value": null,
              "occurs": null,
              "redefines": null,
              "children": []
            }
          ]
        },
        {
          "level": "01",
          "name": "Error-Messages",
          "picture": null,
          "usage": null,
          "value": null,
          "occurs": null,
          "redefines": null,
          "children": [
            {
              "level": "03",
              "name": "PL003",
              "picture": "x(28)",
              "usage": null,
              "value": "PL003",
              "occurs": null,
              "redefines": null,
              "children": []
            },
            {
              "level": "03",
              "name": "PL006",
              "picture": "x(38)",
              "usage": null,
              "value": "PL116",
              "occurs": null,
              "redefines": null,
              "children": []
            },
            {
              "level": "03",
              "name": "PL142",
              "picture": "x(39)",
              "usage": null,
              "value": "PL142",
              "occurs": null,
              "redefines": null,
              "children": []
            },
            {
              "level": "03",
              "name": "PL143",
              "picture": "x(50)",
              "usage": null,
              "value": "PL143",
              "occurs": null,
              "redefines": null,
              "children": []
            },
            {
              "level": "03",
              "name": "PL143B",
              "picture": "x(11)",
              "usage": null,
              "value": "&",
              "occurs": null,
              "redefines": null,
              "children": []
            }
          ]
        }
      ],
      "constants": [
        {
          "level": "77",
          "name": "prog-name",
          "picture": "x(15)",
          "usage": null,
          "value": "PL090",
          "occurs": null,
          "redefines": null,
          "children": []
        },
        {
          "level": "77",
          "name": "ws-ITM5-Length",
          "picture": "999",
          "usage": null,
          "value": "zero",
          "occurs": null,
          "redefines": null,
          "children": []
        },
        {
          "level": "77",
          "name": "ws-ITMS-Length",
          "picture": "999",
          "usage": null,
          "value": "zero",
          "occurs": null,
          "redefines": null,
          "children": []
        }
      ],
      "tables": [],
      "flags": [],
      "counters": [],
      "accumulators": []
    },
    "localStorage": {
      "fields": []
    },
    "linkageSection": {
      "parameters": [
        {
          "level": "01",
          "name": "to-day",
          "picture": "x(10)",
          "usage": null,
          "value": null,
          "occurs": null,
          "redefines": null,
          "children": []
        }
      ]
    }
  },
  "procedure": {
    "divisions": [
      {
        "name": "PROCEDURE DIVISION",
        "using": [
          "ws-calling-data",
          "system-record",
          "to-day",
          "file-defs"
        ]
      }
    ],
    "sections": [],
    "paragraphs": [
      {
        "name": "file-control",
        "statements": [],
        "performedBy": [],
        "performs": []
      },
      {
        "name": "file-defs",
        "statements": [],
        "performedBy": [],
        "performs": []
      },
      {
        "name": "end-if",
        "statements": [],
        "performedBy": [],
        "performs": []
      },
      {
        "name": "menu-exit",
        "statements": [],
        "performedBy": [],
        "performs": []
      },
      {
        "name": "goback",
        "statements": [],
        "performedBy": [],
        "performs": []
      },
      {
        "name": "process-input",
        "statements": [],
        "performedBy": [],
        "performs": []
      },
      {
        "name": "end-of-input",
        "statements": [],
        "performedBy": [],
        "performs": []
      }
    ]
  },
  "dependencies": {
    "copyStatements": [
      {
        "copybook": "of",
        "line": 82,
        "inDivision": "IDENTIFICATION",
        "inSection": null
      }
    ],
    "callStatements": [],
    "sqlStatements": []
  },
  "controlFlow": {
    "performStatements": [
      {
        "type": "PERFORM",
        "target": "sorting-1",
        "thru": null,
        "condition": null,
        "line": 228
      },
      {
        "type": "PERFORM",
        "target": "OTM5-Open-Input",
        "thru": null,
        "condition": null,
        "line": 251
      },
      {
        "type": "PERFORM",
        "target": "OTM5-Close",
        "thru": null,
        "condition": null,
        "line": 253
      },
      {
        "type": "PERFORM",
        "target": "OTM5-Read-Next",
        "thru": null,
        "condition": null,
        "line": 261
      },
      {
        "type": "PERFORM",
        "target": "OTM5-Close",
        "thru": null,
        "condition": null,
        "line": 276
      }
    ],
    "goToStatements": [
      {
        "target": "menu-exit",
        "line": 225,
        "conditional": false
      },
      {
        "target": "main-exit",
        "line": 256,
        "conditional": false
      },
      {
        "target": "end-of-input",
        "line": 263,
        "conditional": false
      },
      {
        "target": "process-input",
        "line": 266,
        "conditional": false
      },
      {
        "target": "process-input",
        "line": 268,
        "conditional": false
      },
      {
        "target": "process-input",
        "line": 271,
        "conditional": false
      }
    ],
    "conditionals": [
      {
        "type": "IF",
        "condition": "n",
        "line": 46,
        "complexity": 1
      },
      {
        "type": "IF",
        "condition": "i",
        "line": 79,
        "complexity": 1
      },
      {
        "type": "IF",
        "condition": "n",
        "line": 83,
        "complexity": 1
      },
      {
        "type": "IF",
        "condition": "n",
        "line": 198,
        "complexity": 1
      },
      {
        "type": "IF",
        "condition": "n",
        "line": 200,
        "complexity": 1
      },
      {
        "type": "IF",
        "condition": "w",
        "line": 209,
        "complexity": 1
      },
      {
        "type": "IF",
        "condition": "*",
        "line": 217,
        "complexity": 1
      },
      {
        "type": "IF",
        "condition": "P",
        "line": 221,
        "complexity": 1
      },
      {
        "type": "IF",
        "condition": "f",
        "line": 252,
        "complexity": 1
      },
      {
        "type": "IF",
        "condition": "f",
        "line": 262,
        "complexity": 1
      },
      {
        "type": "IF",
        "condition": "o",
        "line": 265,
        "complexity": 1
      },
      {
        "type": "IF",
        "condition": "z",
        "line": 267,
        "complexity": 1
      }
    ]
  },
  "businessLogic": {
    "calculations": [],
    "validations": [
      {
        "field": "ws-ITM5-Length",
        "condition": "if       ws-ITM5-Length NOT = ws-ITMS-Length",
        "line": 209,
        "errorHandling": "ELSE clause"
      },
      {
        "field": "P-Flag-P",
        "condition": "if       P-Flag-P = 0",
        "line": 221,
        "errorHandling": "ELSE clause"
      },
      {
        "field": "fs-reply",
        "condition": "if       fs-reply not = zero",
        "line": 252,
        "errorHandling": "ELSE clause"
      },
      {
        "field": "fs-reply",
        "condition": "if       fs-reply = 10",
        "line": 262,
        "errorHandling": "ELSE clause"
      },
      {
        "field": "oi-type",
        "condition": "if       oi-type = 1",
        "line": 265,
        "errorHandling": "ELSE clause"
      },
      {
        "field": "zero",
        "condition": "if       zero = oi-b-nos",
        "line": 267,
        "errorHandling": null
      }
    ],
    "fileOperations": [
      {
        "operation": "READ",
        "file": "open-item-file-5",
        "line": 261,
        "errorHandling": "AT END"
      },
      {
        "operation": "WRITE",
        "file": "to",
        "line": 83,
        "errorHandling": null
      }
    ]
  },
  "metrics": {
    "linesOfCode": 130,
    "linesOfComment": 151,
    "cyclomaticComplexity": 19,
    "numberOfSections": 0,
    "numberOfParagraphs": 7,
    "numberOfCalls": 0,
    "numberOfFiles": 1,
    "numberOfSQLStatements": 0,
    "deepestNesting": 2
  },
  "qualityIndicators": {
    "hasErrorHandling": true,
    "hasComments": true,
    "usesGoTo": true,
    "hasDeadCode": true,
    "followsNamingConventions": false
  }
}